yoda_powers/__init__.py
yoda_powers/bio/__init__.py
yoda_powers/bio/bio.py
yoda_powers/display/__init__.py
yoda_powers/display/display.py
yoda_powers/scripts/__init__.py
yoda_powers/scripts/cli.py
yoda_powers/scripts/filter_mummer.py
yoda_powers/toolbox/__init__.py
yoda_powers/toolbox/toolbox.py
yoda_powers-1.0.1.dist-info/DESCRIPTION.rst
yoda_powers-1.0.1.dist-info/METADATA
yoda_powers-1.0.1.dist-info/RECORD
yoda_powers-1.0.1.dist-info/WHEEL
yoda_powers-1.0.1.dist-info/entry_points.txt
yoda_powers-1.0.1.dist-info/metadata.json
yoda_powers-1.0.1.dist-info/top_level.txt
