Metadata-Version: 2.0
Name: yoda-powers
Version: 1.0.1
Summary: Use it to import very handy functions.
Home-page: https://github.com/sravel/yoda-powers
Author: Sébastien Ravel
Author-email: sebastien.ravel@cirad.fr
License: UNKNOWN
Download-URL: https://github.com/sravel/yoda-powers/archive/1.0.1.tar.gz
Keywords: python
Platform: cross-platform
Platform: Windows i686
Platform: MacOSX AMD64
Classifier: Development Status :: 5 - Production/Stable
Classifier: Environment :: Other Environment
Classifier: Intended Audience :: Developers
Classifier: Intended Audience :: End Users/Desktop
Classifier: License :: OSI Approved :: GNU General Public License v3 (GPLv3)
Classifier: Operating System :: OS Independent
Classifier: Programming Language :: Python :: 3.7
Classifier: Natural Language :: English
Requires-Dist: BioPython
